PasswortFenster/__EntryLabel.py
PasswortFenster/__PasswortMain.py
PasswortFenster/__PasswortSubmit.py
PasswortFenster/__init__.py
PasswortFenster/Konfigurationen/LabelKonfiguration.py
PasswortFenster/Konfigurationen/PasswortWidgetStrings.py
PasswortFenster/Konfigurationen/SubmitWidgetStrings.py
PasswortFenster/Konfigurationen/UserWidgetStrings.py
PasswortFenster/Konfigurationen/WindowKonfigurationen.py
PasswortFenster/Konfigurationen/__init__.py
PasswortFenster/__PasswortEingabeWidget/__PasswortEntry.py
PasswortFenster/__PasswortEingabeWidget/__PasswortShowButton.py
PasswortFenster/__PasswortEingabeWidget/__init__.py
PasswortFenster/__UserEingabeWidget/UserEntry.py
PasswortFenster/__UserEingabeWidget/__init__.py
PasswortFenster-2.0.2.dist-info/LICENSE.txt
PasswortFenster-2.0.2.dist-info/METADATA
PasswortFenster-2.0.2.dist-info/WHEEL
PasswortFenster-2.0.2.dist-info/top_level.txt
PasswortFenster-2.0.2.dist-info/RECORD
