Metadata-Version: 2.1
Name: PasswortFenster
Version: 2.0.2
Summary: Öffnet ein Fenster zur Eingabe von Login-Daten
Home-page: https://github.com/heureka-code/PasswortFenster
Author: heureka-code
License: MIT
Download-URL: https://github.com/heureka-code/PasswortFenster/archive/2.0.2.tar.gz
Keywords: Passwort,Fenster,PyQt5,PasswortFenster,Login,Username
Platform: UNKNOWN
Classifier: Programming Language :: Python :: 3
Classifier: License :: OSI Approved :: GNU General Public License v2 or later (GPLv2+)
Requires-Dist: PyQt5
